microman/__init__.py
microman/background.py
microman/cli.py
microman/conf.py
microman/exceptions.py
microman/files.py
microman/hooks.py
microman/ids.py
microman/introspect.py
microman/lineage.py
microman/logs.py
microman/params.py
microman/registry.py
microman/schedule.py
microman/secrets.py
microman/status.py
microman/stream.py
microman/task.py
microman/time.py
microman/types.py
microman/run/__init__.py
microman/run/base.py
microman/runners/__init__.py
microman/runners/base.py
microman/server/__init__.py
microman/storage/__init__.py
microman/tasks/__init__.py
microman/tasks/bash.py
microman/tasks/http.py
microman/track/__init__.py
microman-0.0.1.dist-info/DESCRIPTION.rst
microman-0.0.1.dist-info/METADATA
microman-0.0.1.dist-info/RECORD
microman-0.0.1.dist-info/WHEEL
microman-0.0.1.dist-info/entry_points.txt
microman-0.0.1.dist-info/metadata.json
microman-0.0.1.dist-info/top_level.txt
tests/__init__.py
tests/test_task.py
