Metadata-Version: 2.0
Name: microman
Version: 0.0.1
Summary: micromanage all of your tasks
Home-page: https://github.com/michalwols/microman
Author: Michal Wolski
Author-email: michalwols@gmail.com
License: MIT
Platform: UNKNOWN
Requires-Python: >=3.7
Provides-Extra: cli
Provides-Extra: cli
Requires-Dist: click (>=6.7); extra == 'cli'
